{"id": "bf4813e756be4b9da78d2693f1ec606c", "name": "sporocystic forthputting", "schedule": [{"campus": "Rockville", "campus_color": "#ff0000", "class_color": "#0c6dda", "course": "ACCT 222", "credits": "4.000", "crn": "30341", "days": {"friday": false, "monday": true, "saturday": false, "sunday": false, "thursday": false, "tuesday": false, "wednesday": true}, "instructor": "James L. Nelson ", "location": "HU 127", "schedule_type": "Lecture", "seats": "-1", "times": {"end": "1900-01-01 12:40:00", "meetings": [{"end": "1900-01-01 12:40:00", "start": "1900-01-01 11:00:00"}, {"end": "1900-01-03 12:40:00", "start": "1900-01-03 11:00:00"}], "start": "1900-01-01 11:00:00", "tba": false}, "title": "ACCOUNTING II - ACCT 222", "waitlist": "0"}], "selected_titles": {"ACCOUNTING II - ACCT 222": [{"crn": "30342", "course": "ACCT 222", "title": "ACCOUNTING II - ACCT 222", "credits": "4.000", "days": {"monday": true, "tuesday": false, "wednesday": true, "thursday": false, "friday": false, "saturday": false, "sunday": false}, "times": {"start": "1900-01-01 08:00:00", "end": "1900-01-01 09:40:00", "tba": false, "meetings": [{"start": "1900-01-01 08:00:00", "end": "1900-01-01 09:40:00"}, {"start": "1900-01-03 08:00:00", "end": "1900-01-03 09:40:00"}]}, "seats": "1", "waitlist": "0", "campus": "Rockville", "location": "HU 207", "instructor": "Sithamparam Sengamalay ", "schedule_type": "Lecture", "campus_color": "#ff0000", "class_color": "#0c6dda"}, {"crn": "30495", "course": "ACCT 222", "title": "ACCOUNTING II - ACCT 222", "credits": "4.000", "days": {"monday": true, "tuesday": false, "wednesday": true, "thursday": false, "friday": false, "saturday": false, "sunday": false}, "times": {"start": "1900-01-01 10:00:00", "end": "1900-01-01 11:40:00", "tba": false, "meetings": [{"start": "1900-01-01 10:00:00", "end": "1900-01-01 11:40:00"}, {"start": "1900-01-03 10:00:00", "end": "1900-01-03 11:40:00"}]}, "seats": "0", "waitlist": "0", "campus": "Germantown", "location": "HT 205", "instructor": "Shahrzad S. Mirbod ", "schedule_type": "Lecture", "campus_color": "#009900", "class_color": "#0c6dda"}, {"crn": "30341", "course": "ACCT 222", "title": "ACCOUNTING II - ACCT 222", "credits": "4.000", "days": {"monday": true, "tuesday": false, "wednesday": true, "thursday": false, "friday": false, "saturday": false, "sunday": false}, "times": {"start": "1900-01-01 11:00:00", "end": "1900-01-01 12:40:00", "tba": false, "meetings": [{"start": "1900-01-01 11:00:00", "end": "1900-01-01 12:40:00"}, {"start": "1900-01-03 11:00:00", "end": "1900-01-03 12:40:00"}]}, "seats": "-1", "waitlist": "0", "campus": "Rockville", "location": "HU 127", "instructor": "James L. Nelson ", "schedule_type": "Lecture", "campus_color": "#ff0000", "class_color": "#0c6dda"}, {"crn": "30049", "course": "ACCT 222", "title": "ACCOUNTING II - ACCT 222", "credits": "4.000", "days": {"monday": true, "tuesday": false, "wednesday": true, "thursday": false, "friday": false, "saturday": false, "sunday": false}, "times": {"start": "1900-01-01 13:00:00", "end": "1900-01-01 14:40:00", "tba": false, "meetings": [{"start": "1900-01-01 13:00:00", "end": "1900-01-01 14:40:00"}, {"start": "1900-01-03 13:00:00", "end": "1900-01-03 14:40:00"}]}, "seats": "23", "waitlist": "0", "campus": "Takoma Park/Silver Spring", "location": "P3 206", "instructor": "Richard A. Gottfried ", "schedule_type": "Lecture", "campus_color": "#0099cc", "class_color": "#0c6dda"}, {"crn": "30497", "course": "ACCT 222", "title": "ACCOUNTING II - ACCT 222", "credits": "4.000", "days": {"monday": true, "tuesday": false, "wednesday": true, "thursday": false, "friday": false, "saturday": false, "sunday": false}, "times": {"start": "1900-01-01 13:00:00", "end": "1900-01-01 14:40:00", "tba": false, "meetings": [{"start": "1900-01-01 13:00:00", "end": "1900-01-01 14:40:00"}, {"start": "1900-01-03 13:00:00", "end": "1900-01-03 14:40:00"}]}, "seats": "1", "waitlist": "0", "campus": "Germantown", "location": "HT 103", "instructor": "Philliph L. Ringeisen ", "schedule_type": "Lecture", "campus_color": "#009900", "class_color": "#0c6dda"}, {"crn": "30065", "course": "ACCT 222", "title": "ACCOUNTING II - ACCT 222", "credits": "4.000", "days": {"monday": false, "tuesday": false, "wednesday": false, "thursday": false, "friday": false, "saturday": false, "sunday": false}, "times": {"start": "", "end": "", "tba": true, "meetings": []}, "seats": "0", "waitlist": "0", "campus": "Distance Learning", "location": "DL WEB", "instructor": "Brian S. Baick ", "schedule_type": "Lecture", "campus_color": "#666699", "class_color": "#0c6dda"}, {"crn": "30344", "course": "ACCT 222", "title": "ACCOUNTING II - ACCT 222", "credits": "4.000", "days": {"monday": false, "tuesday": true, "wednesday": false, "thursday": true, "friday": false, "saturday": false, "sunday": false}, "times": {"start": "1900-01-01 08:00:00", "end": "1900-01-01 09:40:00", "tba": false, "meetings": [{"start": "1900-01-02 08:00:00", "end": "1900-01-02 09:40:00"}, {"start": "1900-01-04 08:00:00", "end": "1900-01-04 09:40:00"}]}, "seats": "20", "waitlist": "0", "campus": "Rockville", "location": "HU 129", "instructor": "Darryl Lesesne ", "schedule_type": "Lecture", "campus_color": "#ff0000", "class_color": "#0c6dda"}, {"crn": "30496", "course": "ACCT 222", "title": "ACCOUNTING II - ACCT 222", "credits": "4.000", "days": {"monday": false, "tuesday": true, "wednesday": false, "thursday": true, "friday": false, "saturday": false, "sunday": false}, "times": {"start": "1900-01-01 09:00:00", "end": "1900-01-01 10:40:00", "tba": false, "meetings": [{"start": "1900-01-02 09:00:00", "end": "1900-01-02 10:40:00"}, {"start": "1900-01-04 09:00:00", "end": "1900-01-04 10:40:00"}]}, "seats": "0", "waitlist": "0", "campus": "Germantown", "location": "HT 205", "instructor": "Denise T. Bossard ", "schedule_type": "Lecture", "campus_color": "#009900", "class_color": "#0c6dda"}, {"crn": "30050", "course": "ACCT 222", "title": "ACCOUNTING II - ACCT 222", "credits": "4.000", "days": {"monday": false, "tuesday": true, "wednesday": false, "thursday": true, "friday": false, "saturday": false, "sunday": false}, "times": {"start": "1900-01-01 11:00:00", "end": "1900-01-01 12:40:00", "tba": false, "meetings": [{"start": "1900-01-02 11:00:00", "end": "1900-01-02 12:40:00"}, {"start": "1900-01-04 11:00:00", "end": "1900-01-04 12:40:00"}]}, "seats": "0", "waitlist": "0", "campus": "Takoma Park/Silver Spring", "location": "ST 328", "instructor": "James A. Baisey ", "schedule_type": "Lecture", "campus_color": "#0099cc", "class_color": "#0c6dda"}, {"crn": "30345", "course": "ACCT 222", "title": "ACCOUNTING II - ACCT 222", "credits": "4.000", "days": {"monday": false, "tuesday": true, "wednesday": false, "thursday": true, "friday": false, "saturday": false, "sunday": false}, "times": {"start": "1900-01-01 14:30:00", "end": "1900-01-01 16:10:00", "tba": false, "meetings": [{"start": "1900-01-02 14:30:00", "end": "1900-01-02 16:10:00"}, {"start": "1900-01-04 14:30:00", "end": "1900-01-04 16:10:00"}]}, "seats": "0", "waitlist": "0", "campus": "Rockville", "location": "SC 259", "instructor": "Denise T. Bossard ", "schedule_type": "Lecture", "campus_color": "#ff0000", "class_color": "#0c6dda"}, {"crn": "33128", "course": "ACCT 222", "title": "ACCOUNTING II - ACCT 222", "credits": "4.000", "days": {"monday": false, "tuesday": true, "wednesday": false, "thursday": true, "friday": false, "saturday": false, "sunday": false}, "times": {"start": "1900-01-01 19:00:00", "end": "1900-01-01 20:40:00", "tba": false, "meetings": [{"start": "1900-01-02 19:00:00", "end": "1900-01-02 20:40:00"}, {"start": "1900-01-04 19:00:00", "end": "1900-01-04 20:40:00"}]}, "seats": "4", "waitlist": "0", "campus": "Germantown", "location": "HT 203", "instructor": "Philliph L. Ringeisen ", "schedule_type": "Lecture", "campus_color": "#009900", "class_color": "#0c6dda"}, {"crn": "30343", "course": "ACCT 222", "title": "ACCOUNTING II - ACCT 222", "credits": "4.000", "days": {"monday": false, "tuesday": true, "wednesday": false, "thursday": false, "friday": false, "saturday": false, "sunday": false}, "times": {"start": "1900-01-01 18:00:00", "end": "1900-01-01 21:40:00", "tba": false, "meetings": [{"start": "1900-01-02 18:00:00", "end": "1900-01-02 21:40:00"}]}, "seats": "-1", "waitlist": "0", "campus": "Rockville", "location": "HU 122", "instructor": "James L. Nelson ", "schedule_type": "Lecture", "campus_color": "#ff0000", "class_color": "#0c6dda"}, {"crn": "32547", "course": "ACCT 222", "title": "ACCOUNTING II - ACCT 222", "credits": "4.000", "days": {"monday": false, "tuesday": false, "wednesday": true, "thursday": false, "friday": false, "saturday": false, "sunday": false}, "times": {"start": "1900-01-01 18:00:00", "end": "1900-01-01 21:55:00", "tba": false, "meetings": [{"start": "1900-01-03 18:00:00", "end": "1900-01-03 21:55:00"}]}, "seats": "11", "waitlist": "0", "campus": "Takoma Park/Silver Spring", "location": "P3 206", "instructor": "James V. Hodge ", "schedule_type": "Lecture", "campus_color": "#0099cc", "class_color": "#0c6dda"}]}, "subjects": []}