[{"crn": "34174", "course": "ADS 039", "title": "INTRODUCTION TO DRAWING - ADS 039", "credits": "2.500", "days": {"monday": false, "tuesday": false, "wednesday": false, "thursday": true, "friday": false, "saturday": false, "sunday": false}, "times": {"start": "1900-01-01 19:00:00", "end": "1900-01-01 21:30:00", "tba": false}, "seats": "8", "waitlist": "0", "campus": "Takoma Park/Silver Spring", "location": "CF 218", "instructor": "Iona R. Brown ", "schedule_type": "On-Campus - Online enhanced", "campus_color": "#0099cc", "class_color": "#1A98A7"}, {"crn": "34177", "course": "ADS 198", "title": "PHOTOSHOP I - ADS 198", "credits": "2.500", "days": {"monday": false, "tuesday": false, "wednesday": false, "thursday": true, "friday": false, "saturday": false, "sunday": false}, "times": {"start": "1900-01-01 19:00:00", "end": "1900-01-01 21:30:00", "tba": false}, "seats": "10", "waitlist": "0", "campus": "Rockville", "location": "TBA", "instructor": "Sean McCormick ", "schedule_type": "On-Campus - Online enhanced", "campus_color": "#ff0000", "class_color": "#5DF61F"}, {"crn": "34178", "course": "ADS 198", "title": "PHOTOSHOP I - ADS 198", "credits": "2.500", "days": {"monday": false, "tuesday": false, "wednesday": true, "thursday": false, "friday": false, "saturday": false, "sunday": false}, "times": {"start": "1900-01-01 18:30:00", "end": "1900-01-01 21:30:00", "tba": false}, "seats": "13", "waitlist": "0", "campus": "Takoma Park/Silver Spring", "location": "CF 221", "instructor": "Jerry D. Truong ", "schedule_type": "Lecture", "campus_color": "#0099cc", "class_color": "#5DF61F"}, {"crn": "34183", "course": "ADS 210", "title": "INDESIGN - ADS 210", "credits": "2.500", "days": {"monday": false, "tuesday": false, "wednesday": false, "thursday": true, "friday": false, "saturday": false, "sunday": false}, "times": {"start": "1900-01-01 19:00:00", "end": "1900-01-01 21:30:00", "tba": false}, "seats": "12", "waitlist": "0", "campus": "Takoma Park/Silver Spring", "location": "CF 222", "instructor": "Alison M. Whitty ", "schedule_type": "On-Campus - Online enhanced", "campus_color": "#0099cc", "class_color": "#354F98"}, {"crn": "34181", "course": "ADS 318", "title": "DIGITAL PHOTOGRAPHY - ADS 318", "credits": "0.000", "days": {"monday": false, "tuesday": false, "wednesday": false, "thursday": false, "friday": false, "saturday": true, "sunday": false}, "times": {"start": "1900-01-01 09:30:00", "end": "1900-01-01 12:30:00", "tba": false}, "seats": "9", "waitlist": "0", "campus": "Rockville", "location": "TC 246", "instructor": "Donovan O. Marks ", "schedule_type": "On-Campus - Online enhanced", "campus_color": "#ff0000", "class_color": "#CFB922"}, {"crn": "34184", "course": "ADS 319", "title": "INTRO/GRAPHIC DESIGN SOFTWARE - ADS 319", "credits": "2.500", "days": {"monday": true, "tuesday": false, "wednesday": false, "thursday": false, "friday": false, "saturday": false, "sunday": false}, "times": {"start": "1900-01-01 19:00:00", "end": "1900-01-01 21:30:00", "tba": false}, "seats": "14", "waitlist": "0", "campus": "Takoma Park/Silver Spring", "location": "CF 221", "instructor": "Karin J. Rodney-Haapala ", "schedule_type": "On-Campus - Online enhanced", "campus_color": "#0099cc", "class_color": "#3B42DD"}, {"crn": "34186", "course": "ADS 339", "title": "COLLAGE AND ASSEMBLAGE - ADS 339", "credits": "2.500", "days": {"monday": false, "tuesday": false, "wednesday": false, "thursday": true, "friday": false, "saturday": false, "sunday": false}, "times": {"start": "1900-01-01 16:00:00", "end": "1900-01-01 18:30:00", "tba": false}, "seats": "2", "waitlist": "0", "campus": "Takoma Park/Silver Spring", "location": "CF 234", "instructor": "Holly L. Trout ", "schedule_type": "On-Campus - Online enhanced", "campus_color": "#0099cc", "class_color": "#37E7DC"}, {"crn": "34187", "course": "ADS 341", "title": "STUDIO PNTG/IND STUDIES/OIL/ - ADS 341", "credits": "2.500", "days": {"monday": false, "tuesday": false, "wednesday": false, "thursday": false, "friday": false, "saturday": true, "sunday": false}, "times": {"start": "1900-01-01 09:30:00", "end": "1900-01-01 12:00:00", "tba": false}, "seats": "-1", "waitlist": "0", "campus": "Takoma Park/Silver Spring", "location": "CF 208", "instructor": "Kaltoum A. Maroufi-Colle ", "schedule_type": "Lecture", "campus_color": "#0099cc", "class_color": "#B740B9"}, {"crn": "34188", "course": "ADS 349", "title": "PAINTING: INTERMED WATERCOLOR - ADS 349", "credits": "2.500", "days": {"monday": true, "tuesday": false, "wednesday": false, "thursday": false, "friday": false, "saturday": false, "sunday": false}, "times": {"start": "1900-01-01 13:00:00", "end": "1900-01-01 15:30:00", "tba": false}, "seats": "4", "waitlist": "0", "campus": "Takoma Park/Silver Spring", "location": "CF 234", "instructor": "Wendelin A. Daniels ", "schedule_type": "On-Campus - Online enhanced", "campus_color": "#0099cc", "class_color": "#CB25AE"}, {"crn": "34189", "course": "ADS 349", "title": "PAINTING: INTERMED WATERCOLOR - ADS 349", "credits": "2.500", "days": {"monday": false, "tuesday": false, "wednesday": true, "thursday": false, "friday": false, "saturday": false, "sunday": false}, "times": {"start": "1900-01-01 13:00:00", "end": "1900-01-01 15:30:00", "tba": false}, "seats": "5", "waitlist": "0", "campus": "Takoma Park/Silver Spring", "location": "CF 234", "instructor": "Wendelin A. Daniels ", "schedule_type": "On-Campus - Online enhanced", "campus_color": "#0099cc", "class_color": "#CB25AE"}, {"crn": "34194", "course": "ADS 375", "title": "DOLL DESIGN AND CONSTRUCTION - ADS 375", "credits": "2.500", "days": {"monday": false, "tuesday": false, "wednesday": false, "thursday": false, "friday": true, "saturday": false, "sunday": false}, "times": {"start": "1900-01-01 10:00:00", "end": "1900-01-01 12:30:00", "tba": false}, "seats": "4", "waitlist": "0", "campus": "Takoma Park/Silver Spring", "location": "CF 234", "instructor": "Wendelin A. Daniels ", "schedule_type": "On-Campus - Online enhanced", "campus_color": "#0099cc", "class_color": "#0A36AC"}, {"crn": "34197", "course": "ADS 391", "title": "VIDEO EDITING PART 1/PREMIERE/ - ADS 391", "credits": "1.350", "days": {"monday": false, "tuesday": false, "wednesday": true, "thursday": false, "friday": false, "saturday": false, "sunday": false}, "times": {"start": "1900-01-01 17:00:00", "end": "1900-01-01 19:45:00", "tba": false}, "seats": "14", "waitlist": "0", "campus": "Germantown", "location": "HT 200", "instructor": "Sowbhagyalakshmi Areke ", "schedule_type": "Lecture", "campus_color": "#009900", "class_color": "#F381CA"}, {"crn": "34196", "course": "ADS 391", "title": "VIDEO EDITING PART 1/PREMIERE/ - ADS 391", "credits": "1.350", "days": {"monday": false, "tuesday": false, "wednesday": true, "thursday": false, "friday": false, "saturday": false, "sunday": false}, "times": {"start": "1900-01-01 18:00:00", "end": "1900-01-01 20:45:00", "tba": false}, "seats": "3", "waitlist": "0", "campus": "Rockville", "location": "TC 246", "instructor": "Maria C. Arellano ", "schedule_type": "Lecture", "campus_color": "#ff0000", "class_color": "#F381CA"}, {"crn": "34198", "course": "ADS 392", "title": "VIDEO EDITING PART II/INC AFT/ - ADS 392", "credits": "1.350", "days": {"monday": false, "tuesday": false, "wednesday": true, "thursday": false, "friday": false, "saturday": false, "sunday": false}, "times": {"start": "1900-01-01 18:00:00", "end": "1900-01-01 20:45:00", "tba": false}, "seats": "9", "waitlist": "0", "campus": "Distance Learning", "location": "DL WEB", "instructor": "Maria C. Arellano ", "schedule_type": "On-Campus - Online enhanced", "campus_color": "#666699", "class_color": "#9DD893"}, {"crn": "34200", "course": "ADS 398", "title": "MOBILE PHONE PHOTOGRAPHY - ADS 398", "credits": "1.250", "days": {"monday": false, "tuesday": false, "wednesday": false, "thursday": true, "friday": false, "saturday": false, "sunday": false}, "times": {"start": "1900-01-01 15:30:00", "end": "1900-01-01 18:00:00", "tba": false}, "seats": "3", "waitlist": "0", "campus": "Rockville", "location": "TC 246", "instructor": "Sean McCormick ", "schedule_type": "On-Campus - Online enhanced", "campus_color": "#ff0000", "class_color": "#C134B2"}, {"crn": "34199", "course": "ADS 398", "title": "MOBILE PHONE PHOTOGRAPHY - ADS 398", "credits": "1.250", "days": {"monday": false, "tuesday": false, "wednesday": false, "thursday": true, "friday": false, "saturday": false, "sunday": false}, "times": {"start": "1900-01-01 19:00:00", "end": "1900-01-01 21:30:00", "tba": false}, "seats": "13", "waitlist": "0", "campus": "Takoma Park/Silver Spring", "location": "CF 221", "instructor": "Jerry D. Truong ", "schedule_type": "On-Campus - Online enhanced", "campus_color": "#0099cc", "class_color": "#C134B2"}, {"crn": "34205", "course": "ADS 404", "title": "THE ART DOLL: COSTUMES AND ACC - ADS 404", "credits": "2.500", "days": {"monday": false, "tuesday": false, "wednesday": false, "thursday": false, "friday": true, "saturday": false, "sunday": false}, "times": {"start": "1900-01-01 13:30:00", "end": "1900-01-01 16:00:00", "tba": false}, "seats": "4", "waitlist": "0", "campus": "Takoma Park/Silver Spring", "location": "CF 234", "instructor": "Wendelin A. Daniels ", "schedule_type": "On-Campus - Online enhanced", "campus_color": "#0099cc", "class_color": "#0BEB30"}, {"crn": "34206", "course": "ADS 414", "title": "INTRODUCTION TO ACRYLIC PAINTI - ADS 414", "credits": "2.500", "days": {"monday": false, "tuesday": true, "wednesday": false, "thursday": false, "friday": false, "saturday": false, "sunday": false}, "times": {"start": "1900-01-01 09:30:00", "end": "1900-01-01 12:00:00", "tba": false}, "seats": "10", "waitlist": "0", "campus": "Takoma Park/Silver Spring", "location": "CF 208", "instructor": "Iona R. Brown ", "schedule_type": "On-Campus - Online enhanced", "campus_color": "#0099cc", "class_color": "#A8CD4C"}, {"crn": "34208", "course": "ADS 430", "title": "FREE MAC OSX CRASH COURSE - ADS 430", "credits": "0.300", "days": {"monday": false, "tuesday": false, "wednesday": false, "thursday": false, "friday": false, "saturday": true, "sunday": false}, "times": {"start": "1900-01-01 09:30:00", "end": "1900-01-01 12:30:00", "tba": false}, "seats": "3", "waitlist": "0", "campus": "Takoma Park/Silver Spring", "location": "CF 221", "instructor": "Maria C. Arellano ", "schedule_type": "Lecture", "campus_color": "#0099cc", "class_color": "#A88C93"}, {"crn": "34209", "course": "ADS 430", "title": "FREE MAC OSX CRASH COURSE - ADS 430", "credits": "0.300", "days": {"monday": false, "tuesday": false, "wednesday": false, "thursday": false, "friday": false, "saturday": true, "sunday": false}, "times": {"start": "1900-01-01 14:30:00", "end": "1900-01-01 17:30:00", "tba": false}, "seats": "0", "waitlist": "0", "campus": "Rockville", "location": "TC 246", "instructor": "Maria C. Arellano ", "schedule_type": "Lecture", "campus_color": "#ff0000", "class_color": "#A88C93"}, {"crn": "34210", "course": "ADS 433", "title": "PAPER CRAFTS - ADS 433", "credits": "2.500", "days": {"monday": false, "tuesday": true, "wednesday": false, "thursday": false, "friday": false, "saturday": false, "sunday": false}, "times": {"start": "1900-01-01 10:00:00", "end": "1900-01-01 12:30:00", "tba": false}, "seats": "9", "waitlist": "0", "campus": "Rockville", "location": "GU 240", "instructor": "Wanjin Kim ", "schedule_type": "On-Campus - Online enhanced", "campus_color": "#ff0000", "class_color": "#96AD4F"}, {"crn": "34213", "course": "ADS 449", "title": "CHILDREN'S BOOK ILLUSTRATION - ADS 449", "credits": "2.500", "days": {"monday": false, "tuesday": true, "wednesday": false, "thursday": false, "friday": false, "saturday": false, "sunday": false}, "times": {"start": "1900-01-01 19:00:00", "end": "1900-01-01 21:30:00", "tba": false}, "seats": "0", "waitlist": "0", "campus": "Takoma Park/Silver Spring", "location": "CF 234", "instructor": "Rebecca Solow ", "schedule_type": "On-Campus - Online enhanced", "campus_color": "#0099cc", "class_color": "#0247EE"}, {"crn": "34214", "course": "ADS 456", "title": "SEWING: INTRODUCTION - ADS 456", "credits": "1.250", "days": {"monday": false, "tuesday": false, "wednesday": true, "thursday": false, "friday": false, "saturday": false, "sunday": false}, "times": {"start": "1900-01-01 19:00:00", "end": "1900-01-01 21:30:00", "tba": false}, "seats": "5", "waitlist": "0", "campus": "Distance Learning", "location": "DL WEB", "instructor": "Bridget A. Egan ", "schedule_type": "On-Campus - Online enhanced", "campus_color": "#666699", "class_color": "#E1EBD9"}, {"crn": "34215", "course": "ADS 457", "title": "ACRYLIC PAINTING: INTERMEDIATE - ADS 457", "credits": "2.500", "days": {"monday": false, "tuesday": false, "wednesday": true, "thursday": false, "friday": false, "saturday": false, "sunday": false}, "times": {"start": "1900-01-01 19:00:00", "end": "1900-01-01 21:30:00", "tba": false}, "seats": "11", "waitlist": "0", "campus": "Takoma Park/Silver Spring", "location": "CF 208", "instructor": "Iona R. Brown ", "schedule_type": "On-Campus - Online enhanced", "campus_color": "#0099cc", "class_color": "#15CE03"}, {"crn": "34216", "course": "ADS 460", "title": "DRAWING WRKSHP: DRAWING BASICS - ADS 460", "credits": "0.300", "days": {"monday": false, "tuesday": false, "wednesday": false, "thursday": false, "friday": false, "saturday": true, "sunday": false}, "times": {"start": "1900-01-01 13:00:00", "end": "1900-01-01 16:00:00", "tba": false}, "seats": "0", "waitlist": "0", "campus": "Takoma Park/Silver Spring", "location": "CF 219", "instructor": "Kaltoum A. Maroufi-Colle ", "schedule_type": "Lecture", "campus_color": "#0099cc", "class_color": "#0C52C7"}, {"crn": "34218", "course": "ADS 461", "title": "DRAWING WRKSHP: INK STILL LIFE - ADS 461", "credits": "0.300", "days": {"monday": false, "tuesday": false, "wednesday": false, "thursday": false, "friday": false, "saturday": true, "sunday": false}, "times": {"start": "1900-01-01 13:00:00", "end": "1900-01-01 16:00:00", "tba": false}, "seats": "4", "waitlist": "0", "campus": "Takoma Park/Silver Spring", "location": "CF 219", "instructor": "Kaltoum A. Maroufi-Colle ", "schedule_type": "Lecture", "campus_color": "#0099cc", "class_color": "#CDF28C"}, {"crn": "34219", "course": "ADS 461", "title": "DRAWING WRKSHP: INK STILL LIFE - ADS 461", "credits": "0.300", "days": {"monday": false, "tuesday": false, "wednesday": false, "thursday": false, "friday": true, "saturday": false, "sunday": false}, "times": {"start": "1900-01-01 10:00:00", "end": "1900-01-01 13:00:00", "tba": false}, "seats": "10", "waitlist": "0", "campus": "Germantown", "location": "HS 012", "instructor": "Iona R. Brown ", "schedule_type": "Lecture", "campus_color": "#009900", "class_color": "#CDF28C"}, {"crn": "34221", "course": "ADS 463", "title": "DRAWING WORKSHOP: WATERCOLOR - ADS 463", "credits": "0.300", "days": {"monday": false, "tuesday": false, "wednesday": false, "thursday": false, "friday": false, "saturday": true, "sunday": false}, "times": {"start": "1900-01-01 13:00:00", "end": "1900-01-01 16:00:00", "tba": false}, "seats": "6", "waitlist": "0", "campus": "Takoma Park/Silver Spring", "location": "CF 219", "instructor": "Kaltoum A. Maroufi-Colle ", "schedule_type": "Lecture", "campus_color": "#0099cc", "class_color": "#B8188F"}, {"crn": "34225", "course": "ADS 468", "title": "AQUEOUS MEDIA AND COLLAGE - ADS 468", "credits": "2.500", "days": {"monday": false, "tuesday": false, "wednesday": true, "thursday": false, "friday": false, "saturday": false, "sunday": false}, "times": {"start": "1900-01-01 09:30:00", "end": "1900-01-01 12:00:00", "tba": false}, "seats": "2", "waitlist": "0", "campus": "Takoma Park/Silver Spring", "location": "CF 234", "instructor": "Wendelin A. Daniels ", "schedule_type": "On-Campus - Online enhanced", "campus_color": "#0099cc", "class_color": "#96B39F"}, {"crn": "34283", "course": "ADS 479", "title": "JEWELRY BASICS - ADS 479", "credits": "2.500", "days": {"monday": false, "tuesday": false, "wednesday": false, "thursday": true, "friday": false, "saturday": false, "sunday": false}, "times": {"start": "1900-01-01 10:00:00", "end": "1900-01-01 12:30:00", "tba": false}, "seats": "5", "waitlist": "0", "campus": "Takoma Park/Silver Spring", "location": "CF 234", "instructor": "Wanjin Kim ", "schedule_type": "On-Campus - Online enhanced", "campus_color": "#0099cc", "class_color": "#0D70EC"}, {"crn": "34284", "course": "ADS 482", "title": "SMARTPHONE VIDEO PRODUCTION - ADS 482", "credits": "2.500", "days": {"monday": true, "tuesday": false, "wednesday": false, "thursday": false, "friday": false, "saturday": false, "sunday": false}, "times": {"start": "1900-01-01 13:00:00", "end": "1900-01-01 15:30:00", "tba": false}, "seats": "14", "waitlist": "0", "campus": "Takoma Park/Silver Spring", "location": "CU 106", "instructor": "Biljana Milenkovic ", "schedule_type": "On-Campus - Online enhanced", "campus_color": "#0099cc", "class_color": "#9F48A8"}, {"crn": "35384", "course": "ADS 485", "title": "OIL PAINTING: INTERMEDIATE - ADS 485", "credits": "2.500", "days": {"monday": false, "tuesday": false, "wednesday": false, "thursday": false, "friday": true, "saturday": false, "sunday": false}, "times": {"start": "1900-01-01 16:00:00", "end": "1900-01-01 18:30:00", "tba": false}, "seats": "11", "waitlist": "0", "campus": "Takoma Park/Silver Spring", "location": "CF 208", "instructor": "Kaltoum A. Maroufi-Colle ", "schedule_type": "Lecture", "campus_color": "#0099cc", "class_color": "#E0E72B"}, {"crn": "34297", "course": "ADS 487", "title": "WRITING ABOUT ART - ADS 487", "credits": "1.500", "days": {"monday": false, "tuesday": false, "wednesday": false, "thursday": false, "friday": false, "saturday": true, "sunday": false}, "times": {"start": "1900-01-01 13:00:00", "end": "1900-01-01 14:30:00", "tba": false}, "seats": "11", "waitlist": "0", "campus": "Takoma Park/Silver Spring", "location": "CU 201", "instructor": "Rissa L. Miller ", "schedule_type": "On-Campus - Online enhanced", "campus_color": "#0099cc", "class_color": "#6C5244"}, {"crn": "34310", "course": "ADS 490", "title": "STAINED GLASS: INTRODUCTION - ADS 490", "credits": "1.500", "days": {"monday": false, "tuesday": false, "wednesday": true, "thursday": false, "friday": false, "saturday": false, "sunday": false}, "times": {"start": "1900-01-01 18:30:00", "end": "1900-01-01 21:30:00", "tba": false}, "seats": "1", "waitlist": "0", "campus": "Takoma Park/Silver Spring", "location": "CF 190", "instructor": "David Baxter ", "schedule_type": "Lecture", "campus_color": "#0099cc", "class_color": "#55B6EC"}, {"crn": "34313", "course": "ADS 491", "title": "JEWELRY & METALSMITHING: INTRO - ADS 491", "credits": "3.500", "days": {"monday": false, "tuesday": false, "wednesday": false, "thursday": false, "friday": false, "saturday": true, "sunday": false}, "times": {"start": "1900-01-01 13:00:00", "end": "1900-01-01 18:00:00", "tba": false}, "seats": "2", "waitlist": "0", "campus": "Rockville", "location": "AR 302", "instructor": "Eun-Mee Chung ", "schedule_type": "Lecture", "campus_color": "#ff0000", "class_color": "#698485"}, {"crn": "34322", "course": "ADS 494", "title": "WOODCUT PRINTMAKING: INTRO - ADS 494", "credits": "2.000", "days": {"monday": false, "tuesday": false, "wednesday": false, "thursday": false, "friday": false, "saturday": true, "sunday": false}, "times": {"start": "1900-01-01 10:00:00", "end": "1900-01-01 13:20:00", "tba": false}, "seats": "5", "waitlist": "0", "campus": "Takoma Park/Silver Spring", "location": "CF 210", "instructor": "Jung Min Lee ", "schedule_type": "Lecture", "campus_color": "#0099cc", "class_color": "#86A8D4"}]