[{"crn": "34941", "course": "WPS 081", "title": "PRE-ALG/ALGEBRA FAST TRCK - WPS 081", "credits": "3.000", "days": {"monday": true, "tuesday": true, "wednesday": true, "thursday": true, "friday": true, "saturday": false, "sunday": false}, "times": {"start": "1900-01-01 18:30:00", "end": "1900-01-01 20:30:00", "tba": false, "meetings": [{"start": "1900-01-01 18:30:00", "end": "1900-01-01 20:30:00"}, {"start": "1900-01-02 18:30:00", "end": "1900-01-02 20:30:00"}, {"start": "1900-01-03 18:30:00", "end": "1900-01-03 20:30:00"}, {"start": "1900-01-04 18:30:00", "end": "1900-01-04 20:30:00"}, {"start": "1900-01-05 18:30:00", "end": "1900-01-05 20:30:00"}]}, "seats": "9", "waitlist": "0", "campus": "Rockville", "location": "SC 363", "instructor": "Saba Safa ", "schedule_type": "Lecture", "campus_color": "#ff0000", "class_color": "#1bc7ce"}, {"crn": "34942", "course": "WPS 081", "title": "PRE-ALG/ALGEBRA FAST TRCK - WPS 081", "credits": "3.000", "days": {"monday": false, "tuesday": false, "wednesday": false, "thursday": false, "friday": false, "saturday": true, "sunday": false}, "times": {"start": "1900-01-01 09:00:00", "end": "1900-01-01 12:00:00", "tba": false, "meetings": [{"start": "1900-01-06 09:00:00", "end": "1900-01-06 12:00:00"}]}, "seats": "17", "waitlist": "0", "campus": "Rockville", "location": "SC 363", "instructor": "Andrew Y. Decatus ", "schedule_type": "Lecture", "campus_color": "#ff0000", "class_color": "#1bc7ce"}, {"crn": "34944", "course": "WPS 081", "title": "PRE-ALG/ALGEBRA FAST TRCK - WPS 081", "credits": "3.000", "days": {"monday": false, "tuesday": false, "wednesday": false, "thursday": false, "friday": false, "saturday": true, "sunday": false}, "times": {"start": "1900-01-01 09:00:00", "end": "1900-01-01 12:00:00", "tba": false, "meetings": [{"start": "1900-01-06 09:00:00", "end": "1900-01-06 12:00:00"}]}, "seats": "13", "waitlist": "0", "campus": "Takoma Park/Silver Spring", "location": "CM 220", "instructor": "Khadeejah Smith ", "schedule_type": "Lecture", "campus_color": "#0099cc", "class_color": "#1bc7ce"}]